doctl.py
doctl-0.2.3.dist-info/METADATA
doctl-0.2.3.dist-info/RECORD
doctl-0.2.3.dist-info/WHEEL
doctl-0.2.3.dist-info/top_level.txt
